jetplot/__init__.py
jetplot/chart_utils.py
jetplot/colors.py
jetplot/images.py
jetplot/plots.py
jetplot/signals.py
jetplot/style.py
jetplot/timepiece.py
jetplot-0.6.6.dist-info/licenses/LICENSE.md
jetplot-0.6.6.dist-info/METADATA
jetplot-0.6.6.dist-info/WHEEL
jetplot-0.6.6.dist-info/top_level.txt
jetplot-0.6.6.dist-info/RECORD
