Metadata-Version: 2.4
Name: jetplot
Version: 0.6.6
Summary: jetplot is collection of miscellaneous utils for Matplotlib.
Author-email: Niru Maheswaranathan <niru@hey.com>
License-Expression: MIT
Project-URL: Homepage, https://github.com/nirum/jetplot
Requires-Python: >=3.10
License-File: LICENSE.md
Requires-Dist: numpy>=1.19
Requires-Dist: scipy
Requires-Dist: matplotlib
Requires-Dist: scikit-learn>=1.0.2
Provides-Extra: dev
Requires-Dist: matplotlib-stubs>=0.1.0; extra == "dev"
Requires-Dist: pyrefly>=0.14.0; extra == "dev"
Requires-Dist: pytest>=7.4.4; extra == "dev"
Requires-Dist: pytest-cov>=4.1.0; extra == "dev"
Requires-Dist: ruff>=0.11.10; extra == "dev"
Requires-Dist: scipy-stubs>=1.15.3.0; extra == "dev"
Provides-Extra: docs
Requires-Dist: mkdocs>=1.5.3; extra == "docs"
Requires-Dist: mkdocs-material>=9.2.7; extra == "docs"
Requires-Dist: mkdocstrings[python]>=0.22.0; extra == "docs"
Dynamic: license-file
